saber/__init__.py
saber/assign.py
saber/bs.py
saber/cluster.py
saber/fdc.py
saber/gis.py
saber/io.py
saber/saber.py
saber/table.py
saber_hbc-0.9.0.dist-info/LICENSE
saber_hbc-0.9.0.dist-info/METADATA
saber_hbc-0.9.0.dist-info/WHEEL
saber_hbc-0.9.0.dist-info/top_level.txt
saber_hbc-0.9.0.dist-info/RECORD
